<?xml version="1.0" encoding="UTF-8"?>
<con:soapui-project id="bb8afd44-9d52-43a9-a0bd-732dbb96297e" activeEnvironment="Default" name="Monolith Service Demo Project" resourceRoot="" soapui-version="5.5.0" abortOnError="false" runType="SEQUENTIAL" xmlns:con="http://eviware.com/soapui/config"><con:settings/><con:interface xsi:type="con:RestService" id="74c1fc30-288a-4015-80fc-0601beb583ab" wadlVersion="http://wadl.dev.java.net/2009/02" name="http://localhost:8080" type="rest" xmlns:xsi="http://www.w3.org/2001/XMLSchema-instance"><con:settings/><con:definitionCache type="TEXT" rootPart=""/><con:endpoints><con:endpoint>http://localhost:8080</con:endpoint></con:endpoints><con:resource name="Save" path="/book/save" id="9eff8117-3ccb-4d91-86b0-65a147c9f662"><con:settings/><con:parameters/><con:method name="Save 1" id="a0356116-2cd9-427e-876d-3e5f5993698d" method="POST"><con:settings/><con:parameters/><con:representation type="REQUEST"><con:mediaType>application/json</con:mediaType><con:params/></con:representation><con:representation type="FAULT"><con:mediaType>application/json</con:mediaType><con:status>400</con:status><con:params/><con:element xmlns:save="http://localhost/book/save">save:Fault</con:element></con:representation><con:representation type="RESPONSE"><con:mediaType xsi:nil="true"/><con:status>200</con:status><con:params/><con:element>data</con:element></con:representation><con:representation type="RESPONSE"><con:mediaType xsi:nil="true"/><con:status>200</con:status><con:params/><con:element>data</con:element></con:representation><con:representation type="RESPONSE"><con:mediaType xsi:nil="true"/><con:status>200</con:status><con:params/><con:element>data</con:element></con:representation><con:representation type="RESPONSE"><con:mediaType xsi:nil="true"/><con:status>200</con:status><con:params/><con:element>data</con:element></con:representation><con:request name="Request 1" id="c10fe98e-f9e8-49d9-963b-95e90472f396" mediaType="application/json" postQueryString="false"><con:settings><con:setting id="com.eviware.soapui.impl.wsdl.WsdlRequest@request-headers">&lt;xml-fragment/></con:setting></con:settings><con:endpoint>${#Project#BOOK_SERVICE_URL}</con:endpoint><con:request>{
	"author" : "Teszt",
	"title" : "Az elso konyvem",
	"releaseYear" : 2020
}
</con:request><con:originalUri>http://localhost/book/save</con:originalUri><con:credentials><con:authType>No Authorization</con:authType></con:credentials><con:jmsConfig JMSDeliveryMode="PERSISTENT"/><con:jmsPropertyConfig/><con:parameters/></con:request></con:method></con:resource><con:resource name="all" path="/book/all" id="62bde0ba-b06b-446b-933e-0d912ae84f1c"><con:settings/><con:parameters/><con:method name="Method 1" id="ac904a67-db45-4829-9419-a2a649b85dec" method="GET"><con:settings/><con:parameters/><con:representation type="RESPONSE"><con:mediaType xsi:nil="true"/><con:status>0</con:status><con:params/><con:element>data</con:element></con:representation><con:representation type="RESPONSE"><con:mediaType>application/json</con:mediaType><con:status>200</con:status><con:params/><con:element>Response</con:element></con:representation><con:representation type="RESPONSE"><con:mediaType xsi:nil="true"/><con:status>0</con:status><con:params/><con:element>data</con:element></con:representation><con:request name="Request 1" id="3bb57aea-fd8e-4ced-b79e-0332f14a9e4f" mediaType="application/json"><con:settings><con:setting id="com.eviware.soapui.impl.wsdl.WsdlRequest@request-headers">&lt;xml-fragment/></con:setting></con:settings><con:endpoint>${#Project#BOOK_SERVICE_URL}</con:endpoint><con:request/><con:originalUri>http://localhost/book/all</con:originalUri><con:credentials><con:authType>No Authorization</con:authType></con:credentials><con:jmsConfig JMSDeliveryMode="PERSISTENT"/><con:jmsPropertyConfig/><con:parameters/></con:request></con:method></con:resource><con:resource name="1" path="/book/{id}" id="ae0bd5d1-9e9d-4a09-a3a7-7fd2cc82e3de"><con:settings/><con:parameters><con:parameter><con:name>id</con:name><con:value>4459979650652816044</con:value><con:style>TEMPLATE</con:style><con:default>4459979650652816044</con:default></con:parameter></con:parameters><con:method name="Method 1" id="d5843772-c9df-4cd4-aab2-adb7baf90891" method="GET"><con:settings/><con:parameters/><con:representation type="RESPONSE"><con:mediaType>application/json</con:mediaType><con:status>200</con:status><con:params/><con:element xmlns:ns="http://localhost/book/1">ns:Response</con:element></con:representation><con:request name="Request 1" id="fdeb9f76-b53e-4e4a-b20c-2ce3d3cb29ed" mediaType="application/json"><con:settings><con:setting id="com.eviware.soapui.impl.wsdl.WsdlRequest@request-headers">&lt;xml-fragment/></con:setting></con:settings><con:endpoint>${#Project#BOOK_SERVICE_URL}</con:endpoint><con:request/><con:originalUri>http://localhost/book/1</con:originalUri><con:credentials><con:authType>No Authorization</con:authType></con:credentials><con:jmsConfig JMSDeliveryMode="PERSISTENT"/><con:jmsPropertyConfig/><con:parameters><entry key="id" value="4459979650652816044" xmlns="http://eviware.com/soapui/config"/></con:parameters><con:parameterOrder><con:entry>id</con:entry></con:parameterOrder></con:request></con:method></con:resource><con:resource name="all" path="/order/all" id="ec093a45-8040-40bf-bb64-04a45d798196"><con:settings/><con:parameters/><con:method name="Method 1" id="5abe4839-5945-4617-911a-d77278ef2265" method="GET"><con:settings/><con:parameters/><con:representation type="RESPONSE"><con:mediaType>application/json</con:mediaType><con:status>200</con:status><con:params/><con:element>Response</con:element></con:representation><con:request name="Request 1" id="69e922b2-0ca1-4feb-ad33-8657ca3d6d4e" mediaType="application/json"><con:settings><con:setting id="com.eviware.soapui.impl.wsdl.WsdlRequest@request-headers">&lt;xml-fragment/></con:setting></con:settings><con:endpoint>${#Project#ORDER_SERVICE_URL}</con:endpoint><con:request/><con:originalUri>http://localhost/order/all</con:originalUri><con:credentials><con:authType>No Authorization</con:authType></con:credentials><con:jmsConfig JMSDeliveryMode="PERSISTENT"/><con:jmsPropertyConfig/><con:parameters/></con:request></con:method></con:resource><con:resource name="createDraft" path="/order/createDraft" id="16b00304-3910-4f34-a004-6fef9410ba9f"><con:settings/><con:parameters/><con:method name="Method 1" id="2b39c05a-6a0a-4b38-9fc4-71a980caf4cc" method="POST"><con:settings/><con:parameters/><con:representation type="RESPONSE"><con:mediaType>application/json</con:mediaType><con:status>200</con:status><con:params/><con:element xmlns:cre="http://localhost/order/createDraft">cre:Response</con:element></con:representation><con:representation type="REQUEST"><con:mediaType>application/json</con:mediaType><con:params/></con:representation><con:representation type="FAULT"><con:mediaType>application/json</con:mediaType><con:status>400</con:status><con:params/><con:element xmlns:cre="http://localhost/order/createDraft">cre:Fault</con:element></con:representation><con:request name="Request 1" id="3e77550b-4b91-475a-91ae-6f3f3fe70b41" mediaType="application/json" postQueryString="false"><con:settings><con:setting id="com.eviware.soapui.impl.wsdl.WsdlRequest@request-headers">&lt;xml-fragment/></con:setting></con:settings><con:endpoint>${#Project#ORDER_SERVICE_URL}</con:endpoint><con:request>{
	"orderStatus" : "DRAFT",
	"books" : [ { "id" : 1} ]
}
</con:request><con:originalUri>http://localhost/order/createDraft</con:originalUri><con:credentials><con:authType>No Authorization</con:authType></con:credentials><con:jmsConfig JMSDeliveryMode="PERSISTENT"/><con:jmsPropertyConfig/><con:parameters/></con:request></con:method></con:resource><con:resource name="{id}" path="/order/initPayment/{id}" id="d4832404-226c-4659-8c43-d2b957c0c7d5"><con:settings/><con:parameters><con:parameter><con:name>id</con:name><con:value>id</con:value><con:style>TEMPLATE</con:style><con:default>id</con:default></con:parameter></con:parameters><con:method name="Method 1" id="59453305-76a6-4410-9bea-2a408ceae7f2" method="POST"><con:settings/><con:parameters/><con:representation type="FAULT"><con:mediaType>application/json</con:mediaType><con:status>405 500</con:status><con:params/><con:element xmlns:ns="http://localhost/order/initPayment/4">ns:Fault</con:element></con:representation><con:representation type="REQUEST"><con:mediaType>application/json</con:mediaType><con:params/></con:representation><con:representation type="RESPONSE"><con:mediaType xsi:nil="true"/><con:status>200</con:status><con:params/><con:element>data</con:element></con:representation><con:representation type="RESPONSE"><con:mediaType xsi:nil="true"/><con:status>200</con:status><con:params/><con:element>data</con:element></con:representation><con:representation type="RESPONSE"><con:mediaType xsi:nil="true"/><con:status>200</con:status><con:params/><con:element>data</con:element></con:representation><con:representation type="RESPONSE"><con:mediaType xsi:nil="true"/><con:status>200</con:status><con:params/><con:element>data</con:element></con:representation><con:request name="Request 1" id="fd7b96ca-c503-44f6-8042-dfd8606fe258" mediaType="application/json" postQueryString="false"><con:settings><con:setting id="com.eviware.soapui.impl.wsdl.WsdlRequest@request-headers">&lt;xml-fragment/></con:setting></con:settings><con:endpoint>${#Project#ORDER_SERVICE_URL}</con:endpoint><con:request/><con:originalUri>http://localhost/order/initPayment/4</con:originalUri><con:credentials><con:authType>No Authorization</con:authType></con:credentials><con:jmsConfig JMSDeliveryMode="PERSISTENT"/><con:jmsPropertyConfig/><con:parameters><entry key="id" value="4" xmlns="http://eviware.com/soapui/config"/></con:parameters><con:parameterOrder><con:entry>id</con:entry></con:parameterOrder></con:request></con:method></con:resource><con:resource name="all" path="/payment/all" id="db27ba7d-690a-42f0-93e6-32f765c38380"><con:settings/><con:parameters/><con:method name="Method 1" id="479170c1-615f-4d17-ac53-cfc260a5ce48" method="GET"><con:settings/><con:parameters/><con:representation type="RESPONSE"><con:mediaType>application/json</con:mediaType><con:status>200</con:status><con:params/><con:element>Response</con:element></con:representation><con:request name="Request 1" id="c55071b6-b2ba-4343-b67b-1fce43387b1b" mediaType="application/json"><con:settings><con:setting id="com.eviware.soapui.impl.wsdl.WsdlRequest@request-headers">&lt;xml-fragment/></con:setting></con:settings><con:endpoint>${#Project#PAYMENT_SERVICE_URL}</con:endpoint><con:request/><con:originalUri>http://localhost/payment/all</con:originalUri><con:credentials><con:authType>No Authorization</con:authType></con:credentials><con:jmsConfig JMSDeliveryMode="PERSISTENT"/><con:jmsPropertyConfig/><con:parameters/></con:request></con:method></con:resource></con:interface><con:testSuite id="1c3d3cb3-e82c-4931-a575-b158b5500e85" name="Tests"><con:settings/><con:runType>SEQUENTIAL</con:runType><con:testCase id="8009459f-4332-4c5e-a31f-58d670af0b9b" failOnError="true" failTestCaseOnErrors="true" keepSession="false" maxResults="0" name="Complete process" searchProperties="true"><con:settings/><con:testStep type="restrequest" name="Get all books" id="2f1a8552-487c-4657-8b50-58f5c9a4541a"><con:settings/><con:config service="http://localhost:8080" resourcePath="/book/all" methodName="Method 1" xsi:type="con:RestRequestStep" xmlns:xsi="http://www.w3.org/2001/XMLSchema-instance"><con:restRequest name="Get all books" id="3bb57aea-fd8e-4ced-b79e-0332f14a9e4f" mediaType="application/json"><con:settings><con:setting id="com.eviware.soapui.impl.wsdl.WsdlRequest@request-headers">&lt;xml-fragment/></con:setting></con:settings><con:endpoint>${#Project#BOOK_SERVICE_URL}</con:endpoint><con:request/><con:originalUri>http://localhost/book/all</con:originalUri><con:assertion type="Valid HTTP Status Codes" id="8891e3a1-a0d7-4825-bc79-ee4bcc7e3faf" name="Valid HTTP Status Codes"><con:configuration><codes>200</codes></con:configuration></con:assertion><con:credentials><con:authType>No Authorization</con:authType></con:credentials><con:jmsConfig JMSDeliveryMode="PERSISTENT"/><con:jmsPropertyConfig/><con:parameters/></con:restRequest></con:config></con:testStep><con:testStep type="transfer" name="Property Transfer" id="c172a359-a5e9-4dc6-b14f-98dc9fd4cd9b"><con:settings/><con:config xsi:type="con:PropertyTransfersStep" xmlns:xsi="http://www.w3.org/2001/XMLSchema-instance"><con:transfers setNullOnMissingSource="true" transferTextContent="true" failOnError="true" ignoreEmpty="false" transferToAll="false" entitize="false" transferChildNodes="false"><con:name>bookId</con:name><con:sourceType>Response</con:sourceType><con:sourceStep>Get all books</con:sourceStep><con:sourcePath>$[0].id</con:sourcePath><con:targetType>bookId</con:targetType><con:targetStep>#TestCase#</con:targetStep><con:type>JSONPATH</con:type><con:upgraded>true</con:upgraded></con:transfers></con:config></con:testStep><con:testStep type="restrequest" name="Get one book" id="50ed8517-0ef8-41d5-8840-7c127fd536cd"><con:settings/><con:config service="http://localhost:8080" resourcePath="/book/{id}" methodName="Method 1" xsi:type="con:RestRequestStep" xmlns:xsi="http://www.w3.org/2001/XMLSchema-instance"><con:restRequest name="Get one book" id="fdeb9f76-b53e-4e4a-b20c-2ce3d3cb29ed" mediaType="application/json"><con:settings><con:setting id="com.eviware.soapui.impl.wsdl.WsdlRequest@request-headers">&lt;xml-fragment/></con:setting></con:settings><con:endpoint>${#Project#BOOK_SERVICE_URL}</con:endpoint><con:request/><con:originalUri>http://localhost/book/1</con:originalUri><con:assertion type="Valid HTTP Status Codes" id="757d7522-1f35-455b-9b43-87fc61df5afd" name="Valid HTTP Status Codes"><con:configuration><codes>200</codes></con:configuration></con:assertion><con:credentials><con:authType>No Authorization</con:authType></con:credentials><con:jmsConfig JMSDeliveryMode="PERSISTENT"/><con:jmsPropertyConfig/><con:parameters><entry key="id" value="${#TestCase#bookId}" xmlns="http://eviware.com/soapui/config"/></con:parameters><con:parameterOrder><con:entry>id</con:entry></con:parameterOrder></con:restRequest></con:config></con:testStep><con:testStep type="restrequest" name="Save new order DRAFT" id="69af0e5a-489b-48df-bbd5-9a61bbcaf52e"><con:settings/><con:config service="http://localhost:8080" resourcePath="/order/createDraft" methodName="Method 1" xsi:type="con:RestRequestStep" xmlns:xsi="http://www.w3.org/2001/XMLSchema-instance"><con:restRequest name="Save new order DRAFT" id="3e77550b-4b91-475a-91ae-6f3f3fe70b41" mediaType="application/json" postQueryString="false"><con:settings><con:setting id="com.eviware.soapui.impl.wsdl.WsdlRequest@request-headers">&lt;xml-fragment/></con:setting></con:settings><con:endpoint>${#Project#ORDER_SERVICE_URL}</con:endpoint><con:request>{
	"orderStatus" : "DRAFT",
	"books" : [ { "id" : "${#TestCase#bookId}" } ]
}
</con:request><con:originalUri>http://localhost/order/createDraft</con:originalUri><con:assertion type="Valid HTTP Status Codes" id="6e6f1a7f-f46d-4c2a-9fd5-fec42df9655d" name="Valid HTTP Status Codes"><con:configuration><codes>200</codes></con:configuration></con:assertion><con:assertion type="JsonPath Existence Match" id="6a432fed-dd63-4a73-b16f-3843893dcc11" name="Check response content"><con:configuration><path>$.id</path><content>true</content><allowWildcards>false</allowWildcards><ignoreNamspaceDifferences>false</ignoreNamspaceDifferences><ignoreComments>false</ignoreComments></con:configuration></con:assertion><con:credentials><con:authType>No Authorization</con:authType></con:credentials><con:jmsConfig JMSDeliveryMode="PERSISTENT"/><con:jmsPropertyConfig/><con:parameters/></con:restRequest></con:config></con:testStep><con:testStep type="transfer" name="Property Transfer 2" id="6cc4dc83-74ed-4694-995d-85a15e3b9558"><con:settings/><con:config xsi:type="con:PropertyTransfersStep" xmlns:xsi="http://www.w3.org/2001/XMLSchema-instance"><con:transfers setNullOnMissingSource="true" transferTextContent="true" failOnError="true" ignoreEmpty="false" transferToAll="false" entitize="false" transferChildNodes="false"><con:name>orderId</con:name><con:sourceType>Response</con:sourceType><con:sourceStep>Save new order DRAFT</con:sourceStep><con:sourcePath>$.id</con:sourcePath><con:targetType>orderId</con:targetType><con:targetStep>#TestCase#</con:targetStep><con:type>JSONPATH</con:type><con:targetTransferType>JSONPATH</con:targetTransferType><con:upgraded>true</con:upgraded></con:transfers></con:config></con:testStep><con:testStep type="restrequest" name="Start payment" id="00d3b269-8637-47c0-b037-e2d3b8e01985"><con:settings/><con:config service="http://localhost:8080" resourcePath="/order/initPayment/{id}" methodName="Method 1" xsi:type="con:RestRequestStep" xmlns:xsi="http://www.w3.org/2001/XMLSchema-instance"><con:restRequest name="Start payment" id="fd7b96ca-c503-44f6-8042-dfd8606fe258" mediaType="application/json" postQueryString="false"><con:settings><con:setting id="com.eviware.soapui.impl.wsdl.WsdlRequest@request-headers">&lt;xml-fragment/></con:setting></con:settings><con:endpoint>${#Project#ORDER_SERVICE_URL}</con:endpoint><con:request/><con:originalUri>http://localhost/order/initPayment/4</con:originalUri><con:assertion type="Valid HTTP Status Codes" id="9f8660f7-9c92-4b1e-8654-38511ae4564b" name="Valid HTTP Status Codes"><con:configuration><codes>200</codes></con:configuration></con:assertion><con:credentials><con:authType>No Authorization</con:authType></con:credentials><con:jmsConfig JMSDeliveryMode="PERSISTENT"/><con:jmsPropertyConfig/><con:parameters><entry key="id" value="${#TestCase#orderId}" xmlns="http://eviware.com/soapui/config"/></con:parameters><con:parameterOrder><con:entry>id</con:entry></con:parameterOrder></con:restRequest></con:config></con:testStep><con:testStep type="restrequest" name="Get all payments" id="325c1eb6-f825-4490-88c6-54e109a2f9ff"><con:settings/><con:config service="http://localhost:8080" resourcePath="/payment/all" methodName="Method 1" xsi:type="con:RestRequestStep" xmlns:xsi="http://www.w3.org/2001/XMLSchema-instance"><con:restRequest name="Get all payments" id="c55071b6-b2ba-4343-b67b-1fce43387b1b" mediaType="application/json"><con:settings><con:setting id="com.eviware.soapui.impl.wsdl.WsdlRequest@request-headers">&lt;xml-fragment/></con:setting></con:settings><con:endpoint>${#Project#PAYMENT_SERVICE_URL}</con:endpoint><con:request/><con:originalUri>http://localhost/payment/all</con:originalUri><con:assertion type="Valid HTTP Status Codes" id="721e7f7a-87eb-4d1e-9eed-40a125d8e4a2" name="Valid HTTP Status Codes"><con:configuration><codes>200</codes></con:configuration></con:assertion><con:credentials><con:authType>No Authorization</con:authType></con:credentials><con:jmsConfig JMSDeliveryMode="PERSISTENT"/><con:jmsPropertyConfig/><con:parameters/></con:restRequest></con:config></con:testStep><con:properties><con:property><con:name>bookId</con:name><con:value>-2220072961241925744</con:value></con:property><con:property><con:name>orderId</con:name><con:value>1251597168433497216</con:value></con:property></con:properties></con:testCase><con:properties/></con:testSuite><con:properties><con:property><con:name>BOOK_SERVICE_URL</con:name><con:value>http://localhost:8080/</con:value></con:property><con:property><con:name>ORDER_SERVICE_URL</con:name><con:value>http://localhost:8080/</con:value></con:property><con:property><con:name>PAYMENT_SERVICE_URL</con:name><con:value>http://localhost:8080/</con:value></con:property></con:properties><con:wssContainer/><con:oAuth2ProfileContainer/><con:oAuth1ProfileContainer/></con:soapui-project>